ttracker/__init__.py
ttracker/cli_factory.py
ttracker/commands.py
ttracker/entrypoint.py
ttracker/models.py
ttracker/orm.py
ttracker/services.py
ttracker-0.4.2.dist-info/LICENSE
ttracker-0.4.2.dist-info/METADATA
ttracker-0.4.2.dist-info/WHEEL
ttracker-0.4.2.dist-info/entry_points.txt
ttracker-0.4.2.dist-info/RECORD
